COPYING
ChangeLog
MANIFEST.in
NEWS
README
setup.cfg
setup.py
examples/u2f_server.py
examples/yubiauth_server.py
python_u2flib_server.egg-info/PKG-INFO
python_u2flib_server.egg-info/SOURCES.txt
python_u2flib_server.egg-info/dependency_links.txt
python_u2flib_server.egg-info/requires.txt
python_u2flib_server.egg-info/top_level.txt
test/soft_u2f_v2.py
test/test_attestation.py
test/test_jsapi.py
test/test_matchers.py
test/test_serialization.py
test/test_u2f_highlevel.py
test/test_u2f_v2.py
test/test_utils.py
u2flib_server/__init__.py
u2flib_server/jsapi.py
u2flib_server/u2f.py
u2flib_server/u2f_v2.py
u2flib_server/utils.py
u2flib_server/attestation/__init__.py
u2flib_server/attestation/data.py
u2flib_server/attestation/matchers.py
u2flib_server/attestation/metadata.py
u2flib_server/attestation/resolvers.py
u2flib_server/yubicommon/__init__.py
u2flib_server/yubicommon/compat.py
u2flib_server/yubicommon/setup/__init__.py
u2flib_server/yubicommon/setup/cli.py
u2flib_server/yubicommon/setup/exe.py
u2flib_server/yubicommon/setup/pyinstaller_spec.py
u2flib_server/yubicommon/setup/qt.py